configs/__init__.py
dd_ranking/__init__.py
dd_ranking/aug/__init__.py
dd_ranking/aug/cutmix.py
dd_ranking/aug/dsa.py
dd_ranking/aug/mixup.py
dd_ranking/aug/zca.py
dd_ranking/config/__init__.py
dd_ranking/config/user_config.py
dd_ranking/loss/__init__.py
dd_ranking/loss/kl.py
dd_ranking/loss/sce.py
dd_ranking/metrics/__init__.py
dd_ranking/metrics/dd_ranking_aug.py
dd_ranking/metrics/general.py
dd_ranking/metrics/hard_label.py
dd_ranking/metrics/soft_label.py
dd_ranking/utils/__init__.py
dd_ranking/utils/data.py
dd_ranking/utils/misc.py
dd_ranking/utils/model.py
dd_ranking/utils/networks.py
dd_ranking/utils/train_and_eval.py
ddranking/__init__.py
ddranking/aug/__init__.py
ddranking/aug/cutmix.py
ddranking/aug/dsa.py
ddranking/aug/mixup.py
ddranking/aug/zca.py
ddranking/config/__init__.py
ddranking/config/user_config.py
ddranking/loss/__init__.py
ddranking/loss/kl.py
ddranking/loss/mse_gt.py
ddranking/loss/sce.py
ddranking/metrics/__init__.py
ddranking/metrics/aug_robust.py
ddranking/metrics/ddranking_aug.py
ddranking/metrics/general.py
ddranking/metrics/hard_label.py
ddranking/metrics/soft_label.py
ddranking/utils/__init__.py
ddranking/utils/data.py
ddranking/utils/meter.py
ddranking/utils/misc.py
ddranking/utils/model.py
ddranking/utils/networks.py
ddranking/utils/train_and_eval.py
ddranking-0.2.0.dist-info/LICENSE
ddranking-0.2.0.dist-info/METADATA
ddranking-0.2.0.dist-info/WHEEL
ddranking-0.2.0.dist-info/top_level.txt
ddranking-0.2.0.dist-info/RECORD
