Metadata-Version: 2.2
Name: ddranking
Version: 0.2.0
Summary: DD-Ranking: Rethinking the Evaluation of Dataset Distillation
Author: DD-Ranking Team
Author-email: lizekai@u.nus.edu
Requires-Python: >=3.8
License-File: LICENSE
Requires-Dist: torch
Requires-Dist: numpy<2.0.0
Requires-Dist: torchvision
Requires-Dist: tqdm
Requires-Dist: scipy<1.16.0
Requires-Dist: kornia
Requires-Dist: timm
Requires-Dist: pandas
Dynamic: author
Dynamic: author-email
Dynamic: requires-python
